pdistmap/__init__.py
pdistmap/map.py
pdistmap/set.py
pdistmap-0.5.0.dist-info/LICENSE
pdistmap-0.5.0.dist-info/METADATA
pdistmap-0.5.0.dist-info/WHEEL
pdistmap-0.5.0.dist-info/RECORD
