Metadata-Version: 2.1
Name: pdistmap
Version: 0.5.0
Summary: This package helps to find the overlap percentage of two probability distributions.
Home-page: https://github.com/rehanguha/pdistmap
License: Apache-2.0
Keywords: probability,distributions,statistics
Author: Rehan Guha
Author-email: rehanguha29@gmail.com
Requires-Python: >=3.7
Classifier: Intended Audience :: Developers
Classifier: Intended Audience :: Information Technology
Classifier: License :: OSI Approved :: Apache Software License
Classifier: Operating System :: OS Independent
Classifier: Programming Language :: Python :: 3
Classifier: Programming Language :: Python :: 3.7
Classifier: Programming Language :: Python :: 3.8
Classifier: Programming Language :: Python :: 3.9
Classifier: Programming Language :: Python :: 3.10
Classifier: Programming Language :: Python :: 3.11
Classifier: Programming Language :: Python :: 3.12
Classifier: Topic :: Scientific/Engineering
Classifier: Topic :: Scientific/Engineering :: Artificial Intelligence
Classifier: Topic :: Scientific/Engineering :: Mathematics
Classifier: Topic :: Software Development :: Build Tools
Classifier: Topic :: Software Development :: Libraries :: Python Modules
Requires-Dist: numpy (>=1.18)
Requires-Dist: scipy (>=1.5.3)
Project-URL: Repository, https://github.com/rehanguha/pdistmap
